neuronpedia/__init__.py
neuronpedia/examples/context_api_key_example.py
neuronpedia/examples/generate_graph.ipynb
neuronpedia/examples/get_sae_feature.ipynb
neuronpedia/examples/llama_3.3_70b_instruct.ipynb
neuronpedia/examples/new-model.ipynb
neuronpedia/examples/steer_completion.ipynb
neuronpedia/examples/upload_features.ipynb
neuronpedia/examples/upload_graph.ipynb
neuronpedia/examples/upload_vector_and_activations.ipynb
neuronpedia/np_activation.py
neuronpedia/np_explanation.py
neuronpedia/np_feature.py
neuronpedia/np_graph_metadata.py
neuronpedia/np_list.py
neuronpedia/np_model.py
neuronpedia/np_sae_feature.py
neuronpedia/np_source.py
neuronpedia/np_source_set.py
neuronpedia/np_vector.py
neuronpedia/requests/activation_request.py
neuronpedia/requests/base_request.py
neuronpedia/requests/feature_request.py
neuronpedia/requests/graph_request.py
neuronpedia/requests/list_request.py
neuronpedia/requests/model_request.py
neuronpedia/requests/sae_feature_request.py
neuronpedia/requests/source_activation_request.py
neuronpedia/requests/source_set_request.py
neuronpedia/requests/steer_request.py
neuronpedia/requests/topk_by_token_request.py
neuronpedia/requests/vector_request.py
neuronpedia/sample_data.py
neuronpedia/types/autointerp/explain/default.py
neuronpedia/types/autointerp/score/embedding.py
neuronpedia/types/autointerp/score/fuzz_detection.py
neuronpedia/types/common/activation.py
neuronpedia/types/common/feature.py
neuronpedia/types/inference/activation/all.py
neuronpedia/types/inference/activation/single.py
neuronpedia/types/inference/activation/topk_by_token.py
neuronpedia/types/inference/steer.py
neuronpedia/types/inference/util.py
neuronpedia/types/webapp/api/sae_eval.py
neuronpedia-1.1.0.dist-info/METADATA
neuronpedia-1.1.0.dist-info/WHEEL
neuronpedia-1.1.0.dist-info/RECORD
